Metadata-Version: 2.1
Name: nyaascraper
Version: 2.0.1
Summary: nyaascraper is an asynchronous Python library for scraping nyaa.si and sukebei.nyaa.si.
Home-page: https://github.com/zrekryu/nyaascraper
Author: Zrekryu
Author-email: zrekryu@gmail.com
Keywords: nyaa,sukebei,torrent,asynchronous,web scraping
Classifier: Development Status :: 5 - Production/Stable
Classifier: Intended Audience :: Developers
Classifier: License :: OSI Approved :: MIT License
Classifier: Operating System :: OS Independent
Classifier: Programming Language :: Python
Classifier: Programming Language :: Python :: 3
Classifier: Topic :: Internet :: WWW/HTTP :: Indexing/Search
Classifier: Topic :: Software Development :: Libraries
Requires-Dist: httpx
Requires-Dist: beautifulsoup4
Requires-Dist: feedparser
